pygfdrivers/__init__.py
pygfdrivers/avantes/__init__.py
pygfdrivers/avantes/avantes_spectro.py
pygfdrivers/avantes/avaspec/__init__.py
pygfdrivers/avantes/avaspec/avaspec.py
pygfdrivers/avantes/avaspec/avaspecx64.dll
pygfdrivers/avantes/avaspec/errors.py
pygfdrivers/avantes/util/__init__.py
pygfdrivers/avantes/util/param_maps.py
pygfdrivers/avantes/util/utilities.py
pygfdrivers/common/__init__.py
pygfdrivers/common/base_command.py
pygfdrivers/common/base_device.py
pygfdrivers/common/base_scope.py
pygfdrivers/common/serial_device.py
pygfdrivers/common/usb_scope.py
pygfdrivers/common/visa_scope.py
pygfdrivers/common/util/__init__.py
pygfdrivers/common/util/logger_manager.py
pygfdrivers/common/util/save_utility.py
pygfdrivers/common/util/utilities.py
pygfdrivers/dtacq/__init__.py
pygfdrivers/dtacq/dtacq_scope.py
pygfdrivers/dtacq/acq400_commands/__init__.py
pygfdrivers/dtacq/acq400_commands/acquire.py
pygfdrivers/dtacq/acq400_commands/trigger.py
pygfdrivers/dtacq/site_modules/__init__.py
pygfdrivers/dtacq/site_modules/acq425.py
pygfdrivers/dtacq/site_modules/acq480.py
pygfdrivers/dtacq/site_modules/base_site.py
pygfdrivers/dtacq/site_modules/modules_map.py
pygfdrivers/dtacq/util/__init__.py
pygfdrivers/dtacq/util/utilities.py
pygfdrivers/gf/__init__.py
pygfdrivers/gf/axuv_digitizer.py
pygfdrivers/gf/gf_visa_digitizer.py
pygfdrivers/gf/commands/__init__.py
pygfdrivers/gf/commands/capture.py
pygfdrivers/gf/commands/channel.py
pygfdrivers/gf/commands/root.py
pygfdrivers/gf/commands/trigger.py
pygfdrivers/gf/util/__init__.py
pygfdrivers/gf/util/utilities.py
pygfdrivers/keysight/__init__.py
pygfdrivers/keysight/keysight_visa_scope.py
pygfdrivers/keysight/util/__init__.py
pygfdrivers/keysight/util/utilities.py
pygfdrivers/keysight/visa_commands/__init__.py
pygfdrivers/keysight/visa_commands/acquire.py
pygfdrivers/keysight/visa_commands/channel.py
pygfdrivers/keysight/visa_commands/common.py
pygfdrivers/keysight/visa_commands/root.py
pygfdrivers-3.1.1.dist-info/METADATA
pygfdrivers-3.1.1.dist-info/WHEEL
pygfdrivers-3.1.1.dist-info/top_level.txt
pygfdrivers-3.1.1.dist-info/RECORD
